cythonparallelargsort/README.MD
cythonparallelargsort/__init__.py
cythonparallelargsort/parallelargsort.h
cythonparallelargsort/requirements.txt
cythonparallelargsort/thirdparty.json
cythonparallelargsort-0.10.dist-info/LICENSE.rst
cythonparallelargsort-0.10.dist-info/METADATA
cythonparallelargsort-0.10.dist-info/WHEEL
cythonparallelargsort-0.10.dist-info/top_level.txt
cythonparallelargsort-0.10.dist-info/RECORD
