Metadata-Version: 2.1
Name: cythonparallelargsort
Version: 0.10
Summary: Parallel argsort with Cython - 2.5x faster than NumPy!
Home-page: https://github.com/hansalemaos/cythonparallelargsort
Author: Johannes Fischer
Author-email: aulasparticularesdealemaosp@gmail.com
License: MIT
Keywords: cython,arrays,argsort,numpy
Classifier: Development Status :: 4 - Beta
Classifier: Programming Language :: Python :: 3 :: Only
Classifier: Programming Language :: Python :: 3.10
Classifier: Topic :: Software Development :: Libraries :: Python Modules
Classifier: Topic :: Utilities
License-File: LICENSE.rst
Requires-Dist: Cython
Requires-Dist: numpy
